code_minimap/__init__.py
code_minimap/py.typed
python_code_minimap-0.1.1.dist-info/WHEEL
python_code_minimap-0.1.1.dist-info/entry_points.txt
python_code_minimap-0.1.1.dist-info/METADATA
python_code_minimap-0.1.1.dist-info/RECORD
