Metadata-Version: 2.3
Name: python-code-minimap
Version: 0.1.1
Summary: Pure Python code minimap render.
Keywords: minimap,code,braille,terminal,visualisation
Author: Josiah Outram Halstead
Author-email: Josiah Outram Halstead <josiah@halstead.email>
License: MIT License
Classifier: Intended Audience :: Developers
Classifier: License :: OSI Approved :: MIT License
Classifier: Operating System :: OS Independent
Classifier: Programming Language :: Python :: 3
Classifier: Programming Language :: Python :: 3.10
Classifier: Programming Language :: Python :: 3.11
Classifier: Programming Language :: Python :: 3.12
Classifier: Programming Language :: Python :: 3.13
Classifier: Programming Language :: Python :: 3.14
Classifier: Topic :: Software Development :: User Interfaces
Classifier: Topic :: Utilities
Requires-Python: >=3.10
Project-URL: Homepage, https://github.com/joouha/euporie/python-code-minimap
Project-URL: Issues, https://github.com/joouha/euporie/python-code-minimap/issues
Project-URL: Repository, https://github.com/joouha/euporie/python-code-minimap.git
